tests/test_version.py
twinfiles/__main__.py
twinfiles/finder.py
twinfiles/version.py
twinfiles-0.0.3.dist-info/LICENSE
twinfiles-0.0.3.dist-info/METADATA
twinfiles-0.0.3.dist-info/WHEEL
twinfiles-0.0.3.dist-info/entry_points.txt
twinfiles-0.0.3.dist-info/top_level.txt
twinfiles-0.0.3.dist-info/RECORD
