Metadata-Version: 2.1
Name: twinfiles
Version: 0.0.3
Summary: Command line tool to find and remove duplicate files
Home-page: https://github.com/joaompinto/twinfiles
Author: João Pinto
Author-email: lamego.pinto@gmail.com
License: MIT
License-File: LICENSE
Requires-Dist: humanize
Requires-Dist: rich
Requires-Dist: typer
